ChaolingQihaoVol3/Dockerfile
ChaolingQihaoVol3/README.md
ChaolingQihaoVol3/__init__.py
ChaolingQihaoVol3/__main__.py
ChaolingQihaoVol3/file.epub
ChaolingQihaoVol3/index.html
ChaolingQihaoVol3/css/__init__.py
ChaolingQihaoVol3/css/annotations.css
ChaolingQihaoVol3/css/main.css
ChaolingQihaoVol3/css/normalize.css
ChaolingQihaoVol3/css/popup.css
ChaolingQihaoVol3/font/__init__.py
ChaolingQihaoVol3/font/fontello.eot
ChaolingQihaoVol3/font/fontello.svg
ChaolingQihaoVol3/font/fontello.ttf
ChaolingQihaoVol3/font/fontello.woff
ChaolingQihaoVol3/img/__init__.py
ChaolingQihaoVol3/img/annotator-glyph-sprite.png
ChaolingQihaoVol3/img/annotator-icon-sprite.png
ChaolingQihaoVol3/img/apple-touch-icon.png
ChaolingQihaoVol3/img/cancelfullscreen.png
ChaolingQihaoVol3/img/close.png
ChaolingQihaoVol3/img/fullscreen.png
ChaolingQihaoVol3/img/loader.gif
ChaolingQihaoVol3/img/menu-icon.png
ChaolingQihaoVol3/img/save.png
ChaolingQihaoVol3/img/saved.png
ChaolingQihaoVol3/img/settings-s.png
ChaolingQihaoVol3/img/settings.png
ChaolingQihaoVol3/img/star.png
ChaolingQihaoVol3/js/__init__.py
ChaolingQihaoVol3/js/epub.js
ChaolingQihaoVol3/js/epub.min.js
ChaolingQihaoVol3/js/epub.min.map
ChaolingQihaoVol3/js/hooks.min.js
ChaolingQihaoVol3/js/hooks.min.map
ChaolingQihaoVol3/js/reader.js
ChaolingQihaoVol3/js/reader.js.map
ChaolingQihaoVol3/js/reader.min.js
ChaolingQihaoVol3/js/reader.min.map
ChaolingQihaoVol3/js/hooks/__init__.py
ChaolingQihaoVol3/js/hooks/extensions/__init__.py
ChaolingQihaoVol3/js/hooks/extensions/highlight.js
ChaolingQihaoVol3/js/libs/__init__.py
ChaolingQihaoVol3/js/libs/jquery.min.js
ChaolingQihaoVol3/js/libs/localforage.min.js
ChaolingQihaoVol3/js/libs/screenfull.js
ChaolingQihaoVol3/js/libs/screenfull.min.js
ChaolingQihaoVol3/js/libs/zip.min.js
ChaolingQihaoVol3/js/plugins/__init__.py
ChaolingQihaoVol3/js/plugins/hypothesis.js
ChaolingQihaoVol3/js/plugins/search.js
chaoling_qihao_vol3-2022.10.9.1.dist-info/METADATA
chaoling_qihao_vol3-2022.10.9.1.dist-info/WHEEL
chaoling_qihao_vol3-2022.10.9.1.dist-info/entry_points.txt
chaoling_qihao_vol3-2022.10.9.1.dist-info/top_level.txt
chaoling_qihao_vol3-2022.10.9.1.dist-info/RECORD
